<?xml version="1.0" encoding="utf-8"?>
<annotation>
	<source>
		<filename>10205.tif</filename>
		<origin>GF2/GF3</origin>
	</source>
	<research>
		<version>1.0</version>
		<provider>FAIR1M</provider>
		<author>Cyber</author>
		<pluginname>FAIR1M</pluginname>
		<pluginclass>object detection</pluginclass>
		<time>2021-07-21</time>
	</research>
	<size>
		<width>800</width>
		<height>600</height>
		<depth>3</depth>
	</size>
	<objects>
		<object>
			<coordinate>pixel</coordinate>
			<type>rectangle</type>
			<description>None</description>
			<possibleresult>
				<name>other-airplane</name>
			</possibleresult>
			<points>
				<point>346.000000,84.000000</point>
				<point>341.000000,120.000000</point>
				<point>307.000000,115.000000</point>
				<point>312.000000,79.000000</point>
				<point>346.000000,84.000000</point>
			</points>
		</object>
		<object>
			<coordinate>pixel</coordinate>
			<type>rectangle</type>
			<description>None</description>
			<possibleresult>
				<name>other-airplane</name>
			</possibleresult>
			<points>
				<point>341.000000,197.000000</point>
				<point>317.000000,222.000000</point>
				<point>296.000000,202.000000</point>
				<point>320.000000,177.000000</point>
				<point>341.000000,197.000000</point>
			</points>
		</object>
		<object>
			<coordinate>pixel</coordinate>
			<type>rectangle</type>
			<description>None</description>
			<possibleresult>
				<name>other-airplane</name>
			</possibleresult>
			<points>
				<point>376.000000,379.000000</point>
				<point>340.000000,385.000000</point>
				<point>335.000000,356.000000</point>
				<point>371.000000,350.000000</point>
				<point>376.000000,379.000000</point>
			</points>
		</object>
		<object>
			<coordinate>pixel</coordinate>
			<type>rectangle</type>
			<description>None</description>
			<possibleresult>
				<name>A220</name>
			</possibleresult>
			<points>
				<point>87.000000,413.000000</point>
				<point>82.000000,460.000000</point>
				<point>38.000000,455.000000</point>
				<point>43.000000,408.000000</point>
				<point>87.000000,413.000000</point>
			</points>
		</object>
		<object>
			<coordinate>pixel</coordinate>
			<type>rectangle</type>
			<description>None</description>
			<possibleresult>
				<name>A220</name>
			</possibleresult>
			<points>
				<point>143.000000,421.000000</point>
				<point>137.000000,468.000000</point>
				<point>95.000000,462.000000</point>
				<point>101.000000,415.000000</point>
				<point>143.000000,421.000000</point>
			</points>
		</object>
		<object>
			<coordinate>pixel</coordinate>
			<type>rectangle</type>
			<description>None</description>
			<possibleresult>
				<name>Intersection</name>
			</possibleresult>
			<points>
				<point>762.000000,470.000000</point>
				<point>751.000000,511.000000</point>
				<point>707.000000,499.000000</point>
				<point>718.000000,459.000000</point>
				<point>762.000000,470.000000</point>
			</points>
		</object>
		<object>
			<coordinate>pixel</coordinate>
			<type>rectangle</type>
			<description>None</description>
			<possibleresult>
				<name>Intersection</name>
			</possibleresult>
			<points>
				<point>540.000000,358.000000</point>
				<point>518.000000,391.000000</point>
				<point>494.000000,375.000000</point>
				<point>516.000000,342.000000</point>
				<point>540.000000,358.000000</point>
			</points>
		</object>
	</objects>
</annotation>