<?xml version="1.0" encoding="utf-8"?>
<annotation>
	<source>
		<filename>12098.tif</filename>
		<origin>GF2/GF3</origin>
	</source>
	<research>
		<version>1.0</version>
		<provider>FAIR1M</provider>
		<author>Cyber</author>
		<pluginname>FAIR1M</pluginname>
		<pluginclass>object detection</pluginclass>
		<time>2021-07-21</time>
	</research>
	<size>
		<width>1000</width>
		<height>1000</height>
		<depth>3</depth>
	</size>
	<objects>
		<object>
			<coordinate>pixel</coordinate>
			<type>rectangle</type>
			<description>None</description>
			<possibleresult>
				<name>Liquid Cargo Ship</name>
			</possibleresult>
			<points>
				<point>631.000000,357.000000</point>
				<point>491.000000,332.000000</point>
				<point>487.000000,356.000000</point>
				<point>627.000000,381.000000</point>
				<point>631.000000,357.000000</point>
			</points>
		</object>
		<object>
			<coordinate>pixel</coordinate>
			<type>rectangle</type>
			<description>None</description>
			<possibleresult>
				<name>Dry Cargo Ship</name>
			</possibleresult>
			<points>
				<point>929.000000,560.000000</point>
				<point>1006.000000,675.000000</point>
				<point>1018.000000,667.000000</point>
				<point>942.000000,552.000000</point>
				<point>929.000000,560.000000</point>
			</points>
		</object>
		<object>
			<coordinate>pixel</coordinate>
			<type>rectangle</type>
			<description>None</description>
			<possibleresult>
				<name>Dry Cargo Ship</name>
			</possibleresult>
			<points>
				<point>886.000000,562.000000</point>
				<point>964.000000,674.000000</point>
				<point>982.000000,662.000000</point>
				<point>904.000000,550.000000</point>
				<point>886.000000,562.000000</point>
			</points>
		</object>
		<object>
			<coordinate>pixel</coordinate>
			<type>rectangle</type>
			<description>None</description>
			<possibleresult>
				<name>Dry Cargo Ship</name>
			</possibleresult>
			<points>
				<point>915.000000,563.000000</point>
				<point>988.000000,676.000000</point>
				<point>1000.000000,668.000000</point>
				<point>927.000000,555.000000</point>
				<point>915.000000,563.000000</point>
			</points>
		</object>
		<object>
			<coordinate>pixel</coordinate>
			<type>rectangle</type>
			<description>None</description>
			<possibleresult>
				<name>Dry Cargo Ship</name>
			</possibleresult>
			<points>
				<point>874.000000,572.000000</point>
				<point>953.000000,686.000000</point>
				<point>964.000000,678.000000</point>
				<point>886.000000,564.000000</point>
				<point>874.000000,572.000000</point>
			</points>
		</object>
		<object>
			<coordinate>pixel</coordinate>
			<type>rectangle</type>
			<description>None</description>
			<possibleresult>
				<name>Dry Cargo Ship</name>
			</possibleresult>
			<points>
				<point>852.000000,576.000000</point>
				<point>948.000000,717.000000</point>
				<point>965.000000,705.000000</point>
				<point>869.000000,565.000000</point>
				<point>852.000000,576.000000</point>
			</points>
		</object>
		<object>
			<coordinate>pixel</coordinate>
			<type>rectangle</type>
			<description>None</description>
			<possibleresult>
				<name>Motorboat</name>
			</possibleresult>
			<points>
				<point>699.000000,727.000000</point>
				<point>677.000000,743.000000</point>
				<point>681.000000,749.000000</point>
				<point>703.000000,734.000000</point>
				<point>699.000000,727.000000</point>
			</points>
		</object>
		<object>
			<coordinate>pixel</coordinate>
			<type>rectangle</type>
			<description>None</description>
			<possibleresult>
				<name>Motorboat</name>
			</possibleresult>
			<points>
				<point>765.000000,535.000000</point>
				<point>787.000000,536.000000</point>
				<point>788.000000,530.000000</point>
				<point>765.000000,529.000000</point>
				<point>765.000000,535.000000</point>
			</points>
		</object>
		<object>
			<coordinate>pixel</coordinate>
			<type>rectangle</type>
			<description>None</description>
			<possibleresult>
				<name>Fishing Boat</name>
			</possibleresult>
			<points>
				<point>858.000000,803.000000</point>
				<point>835.000000,818.000000</point>
				<point>839.000000,824.000000</point>
				<point>862.000000,810.000000</point>
				<point>858.000000,803.000000</point>
			</points>
		</object>
		<object>
			<coordinate>pixel</coordinate>
			<type>rectangle</type>
			<description>None</description>
			<possibleresult>
				<name>Fishing Boat</name>
			</possibleresult>
			<points>
				<point>876.000000,829.000000</point>
				<point>856.000000,848.000000</point>
				<point>862.000000,855.000000</point>
				<point>883.000000,836.000000</point>
				<point>876.000000,829.000000</point>
			</points>
		</object>
		<object>
			<coordinate>pixel</coordinate>
			<type>rectangle</type>
			<description>None</description>
			<possibleresult>
				<name>Fishing Boat</name>
			</possibleresult>
			<points>
				<point>875.000000,846.000000</point>
				<point>858.000000,858.000000</point>
				<point>862.000000,864.000000</point>
				<point>879.000000,852.000000</point>
				<point>875.000000,846.000000</point>
			</points>
		</object>
		<object>
			<coordinate>pixel</coordinate>
			<type>rectangle</type>
			<description>None</description>
			<possibleresult>
				<name>Dry Cargo Ship</name>
			</possibleresult>
			<points>
				<point>931.000000,878.000000</point>
				<point>894.000000,900.000000</point>
				<point>898.000000,908.000000</point>
				<point>936.000000,886.000000</point>
				<point>931.000000,878.000000</point>
			</points>
		</object>
		<object>
			<coordinate>pixel</coordinate>
			<type>rectangle</type>
			<description>None</description>
			<possibleresult>
				<name>Motorboat</name>
			</possibleresult>
			<points>
				<point>675.000000,702.000000</point>
				<point>657.000000,715.000000</point>
				<point>659.000000,719.000000</point>
				<point>678.000000,707.000000</point>
				<point>675.000000,702.000000</point>
			</points>
		</object>
	</objects>
</annotation>