<?xml version="1.0" encoding="utf-8"?>
<annotation>
	<source>
		<filename>2876.tif</filename>
		<origin>GF2/GF3</origin>
	</source>
	<research>
		<version>1.0</version>
		<provider>FAIR1M</provider>
		<author>Cyber</author>
		<pluginname>FAIR1M</pluginname>
		<pluginclass>object detection</pluginclass>
		<time>2021-07-21</time>
	</research>
	<size>
		<width>600</width>
		<height>800</height>
		<depth>4</depth>
	</size>
	<objects>
		<object>
			<coordinate>pixel</coordinate>
			<type>rectangle</type>
			<description>None</description>
			<possibleresult>
				<name>Small Car</name>
			</possibleresult>
			<points>
				<point>37.000000,643.000000</point>
				<point>34.000000,650.000000</point>
				<point>17.000000,642.000000</point>
				<point>20.000000,635.000000</point>
				<point>37.000000,643.000000</point>
			</points>
		</object>
		<object>
			<coordinate>pixel</coordinate>
			<type>rectangle</type>
			<description>None</description>
			<possibleresult>
				<name>Small Car</name>
			</possibleresult>
			<points>
				<point>43.000000,635.000000</point>
				<point>39.000000,644.000000</point>
				<point>21.000000,635.000000</point>
				<point>26.000000,627.000000</point>
				<point>43.000000,635.000000</point>
			</points>
		</object>
		<object>
			<coordinate>pixel</coordinate>
			<type>rectangle</type>
			<description>None</description>
			<possibleresult>
				<name>Small Car</name>
			</possibleresult>
			<points>
				<point>266.000000,579.000000</point>
				<point>259.000000,587.000000</point>
				<point>243.000000,575.000000</point>
				<point>249.000000,567.000000</point>
				<point>266.000000,579.000000</point>
			</points>
		</object>
		<object>
			<coordinate>pixel</coordinate>
			<type>rectangle</type>
			<description>None</description>
			<possibleresult>
				<name>Small Car</name>
			</possibleresult>
			<points>
				<point>275.000000,629.000000</point>
				<point>252.000000,629.000000</point>
				<point>252.000000,620.000000</point>
				<point>275.000000,620.000000</point>
				<point>275.000000,629.000000</point>
			</points>
		</object>
		<object>
			<coordinate>pixel</coordinate>
			<type>rectangle</type>
			<description>None</description>
			<possibleresult>
				<name>Small Car</name>
			</possibleresult>
			<points>
				<point>314.000000,675.000000</point>
				<point>304.000000,680.000000</point>
				<point>297.000000,666.000000</point>
				<point>307.000000,661.000000</point>
				<point>314.000000,675.000000</point>
			</points>
		</object>
		<object>
			<coordinate>pixel</coordinate>
			<type>rectangle</type>
			<description>None</description>
			<possibleresult>
				<name>Small Car</name>
			</possibleresult>
			<points>
				<point>326.000000,659.000000</point>
				<point>317.000000,665.000000</point>
				<point>311.000000,655.000000</point>
				<point>320.000000,649.000000</point>
				<point>326.000000,659.000000</point>
			</points>
		</object>
		<object>
			<coordinate>pixel</coordinate>
			<type>rectangle</type>
			<description>None</description>
			<possibleresult>
				<name>Small Car</name>
			</possibleresult>
			<points>
				<point>324.000000,618.000000</point>
				<point>319.000000,625.000000</point>
				<point>300.000000,613.000000</point>
				<point>306.000000,605.000000</point>
				<point>324.000000,618.000000</point>
			</points>
		</object>
		<object>
			<coordinate>pixel</coordinate>
			<type>rectangle</type>
			<description>None</description>
			<possibleresult>
				<name>Dump Truck</name>
			</possibleresult>
			<points>
				<point>525.000000,748.000000</point>
				<point>522.000000,759.000000</point>
				<point>514.000000,756.000000</point>
				<point>518.000000,745.000000</point>
				<point>525.000000,748.000000</point>
			</points>
		</object>
		<object>
			<coordinate>pixel</coordinate>
			<type>rectangle</type>
			<description>None</description>
			<possibleresult>
				<name>Small Car</name>
			</possibleresult>
			<points>
				<point>534.000000,753.000000</point>
				<point>529.000000,762.000000</point>
				<point>522.000000,758.000000</point>
				<point>527.000000,749.000000</point>
				<point>534.000000,753.000000</point>
			</points>
		</object>
		<object>
			<coordinate>pixel</coordinate>
			<type>rectangle</type>
			<description>None</description>
			<possibleresult>
				<name>Small Car</name>
			</possibleresult>
			<points>
				<point>546.000000,754.000000</point>
				<point>540.000000,767.000000</point>
				<point>532.000000,764.000000</point>
				<point>537.000000,751.000000</point>
				<point>546.000000,754.000000</point>
			</points>
		</object>
		<object>
			<coordinate>pixel</coordinate>
			<type>rectangle</type>
			<description>None</description>
			<possibleresult>
				<name>Small Car</name>
			</possibleresult>
			<points>
				<point>558.000000,756.000000</point>
				<point>554.000000,770.000000</point>
				<point>545.000000,768.000000</point>
				<point>549.000000,753.000000</point>
				<point>558.000000,756.000000</point>
			</points>
		</object>
		<object>
			<coordinate>pixel</coordinate>
			<type>rectangle</type>
			<description>None</description>
			<possibleresult>
				<name>Small Car</name>
			</possibleresult>
			<points>
				<point>569.000000,757.000000</point>
				<point>568.000000,772.000000</point>
				<point>558.000000,771.000000</point>
				<point>559.000000,756.000000</point>
				<point>569.000000,757.000000</point>
			</points>
		</object>
		<object>
			<coordinate>pixel</coordinate>
			<type>rectangle</type>
			<description>None</description>
			<possibleresult>
				<name>Van</name>
			</possibleresult>
			<points>
				<point>581.000000,773.000000</point>
				<point>574.000000,773.000000</point>
				<point>573.000000,758.000000</point>
				<point>580.000000,758.000000</point>
				<point>581.000000,773.000000</point>
			</points>
		</object>
		<object>
			<coordinate>pixel</coordinate>
			<type>rectangle</type>
			<description>None</description>
			<possibleresult>
				<name>Small Car</name>
			</possibleresult>
			<points>
				<point>461.000000,772.000000</point>
				<point>449.000000,784.000000</point>
				<point>444.000000,779.000000</point>
				<point>455.000000,767.000000</point>
				<point>461.000000,772.000000</point>
			</points>
		</object>
		<object>
			<coordinate>pixel</coordinate>
			<type>rectangle</type>
			<description>None</description>
			<possibleresult>
				<name>Van</name>
			</possibleresult>
			<points>
				<point>469.000000,777.000000</point>
				<point>459.000000,792.000000</point>
				<point>452.000000,787.000000</point>
				<point>462.000000,773.000000</point>
				<point>469.000000,777.000000</point>
			</points>
		</object>
		<object>
			<coordinate>pixel</coordinate>
			<type>rectangle</type>
			<description>None</description>
			<possibleresult>
				<name>Van</name>
			</possibleresult>
			<points>
				<point>479.000000,784.000000</point>
				<point>470.000000,795.000000</point>
				<point>464.000000,790.000000</point>
				<point>473.000000,780.000000</point>
				<point>479.000000,784.000000</point>
			</points>
		</object>
		<object>
			<coordinate>pixel</coordinate>
			<type>rectangle</type>
			<description>None</description>
			<possibleresult>
				<name>Small Car</name>
			</possibleresult>
			<points>
				<point>488.000000,788.000000</point>
				<point>478.000000,800.000000</point>
				<point>472.000000,795.000000</point>
				<point>481.000000,782.000000</point>
				<point>488.000000,788.000000</point>
			</points>
		</object>
	</objects>
</annotation>