<?xml version="1.0" encoding="utf-8"?>
<annotation>
	<source>
		<filename>3196.tif</filename>
		<origin>GF2/GF3</origin>
	</source>
	<research>
		<version>1.0</version>
		<provider>FAIR1M</provider>
		<author>Cyber</author>
		<pluginname>FAIR1M</pluginname>
		<pluginclass>object detection</pluginclass>
		<time>2021-07-21</time>
	</research>
	<size>
		<width>600</width>
		<height>800</height>
		<depth>3</depth>
	</size>
	<objects>
		<object>
			<coordinate>pixel</coordinate>
			<type>rectangle</type>
			<description>None</description>
			<possibleresult>
				<name>Liquid Cargo Ship</name>
			</possibleresult>
			<points>
				<point>496.000000,383.000000</point>
				<point>486.000000,403.000000</point>
				<point>374.000000,343.000000</point>
				<point>385.000000,323.000000</point>
				<point>496.000000,383.000000</point>
			</points>
		</object>
		<object>
			<coordinate>pixel</coordinate>
			<type>rectangle</type>
			<description>None</description>
			<possibleresult>
				<name>Liquid Cargo Ship</name>
			</possibleresult>
			<points>
				<point>244.000000,301.000000</point>
				<point>225.000000,309.000000</point>
				<point>176.000000,201.000000</point>
				<point>196.000000,193.000000</point>
				<point>244.000000,301.000000</point>
			</points>
		</object>
	</objects>
</annotation>