<?xml version="1.0" encoding="utf-8"?>
<annotation>
	<source>
		<filename>6343.tif</filename>
		<origin>GF2/GF3</origin>
	</source>
	<research>
		<version>1.0</version>
		<provider>FAIR1M</provider>
		<author>Cyber</author>
		<pluginname>FAIR1M</pluginname>
		<pluginclass>object detection</pluginclass>
		<time>2021-07-21</time>
	</research>
	<size>
		<width>800</width>
		<height>600</height>
		<depth>4</depth>
	</size>
	<objects>
		<object>
			<coordinate>pixel</coordinate>
			<type>rectangle</type>
			<description>None</description>
			<possibleresult>
				<name>Football Field</name>
			</possibleresult>
			<points>
				<point>104.759300,443.518127</point>
				<point>-103.000000,347.000031</point>
				<point>74.240669,-34.518036</point>
				<point>281.999969,62.000061</point>
				<point>104.759300,443.518127</point>
			</points>
		</object>
		<object>
			<coordinate>pixel</coordinate>
			<type>rectangle</type>
			<description>None</description>
			<possibleresult>
				<name>Baseball Field</name>
			</possibleresult>
			<points>
				<point>746.000000,350.000000</point>
				<point>670.000000,484.000000</point>
				<point>505.000000,389.000000</point>
				<point>581.000000,256.000000</point>
				<point>746.000000,350.000000</point>
			</points>
		</object>
		<object>
			<coordinate>pixel</coordinate>
			<type>rectangle</type>
			<description>None</description>
			<possibleresult>
				<name>Baseball Field</name>
			</possibleresult>
			<points>
				<point>393.000000,394.000000</point>
				<point>349.000000,545.000000</point>
				<point>160.000000,490.000000</point>
				<point>205.000000,338.000000</point>
				<point>393.000000,394.000000</point>
			</points>
		</object>
	</objects>
</annotation>