<?xml version="1.0" encoding="utf-8"?>
<annotation>
	<source>
		<filename>9074.tif</filename>
		<origin>GF2/GF3</origin>
	</source>
	<research>
		<version>1.0</version>
		<provider>FAIR1M</provider>
		<author>Cyber</author>
		<pluginname>FAIR1M</pluginname>
		<pluginclass>object detection</pluginclass>
		<time>2021-07-21</time>
	</research>
	<size>
		<width>1000</width>
		<height>1000</height>
		<depth>3</depth>
	</size>
	<objects>
		<object>
			<coordinate>pixel</coordinate>
			<type>rectangle</type>
			<description>None</description>
			<possibleresult>
				<name>Baseball Field</name>
			</possibleresult>
			<points>
				<point>780.000000,214.000000</point>
				<point>730.000000,329.000000</point>
				<point>598.000000,271.000000</point>
				<point>649.000000,156.000000</point>
				<point>780.000000,214.000000</point>
			</points>
		</object>
		<object>
			<coordinate>pixel</coordinate>
			<type>rectangle</type>
			<description>None</description>
			<possibleresult>
				<name>Van</name>
			</possibleresult>
			<points>
				<point>755.000000,90.000000</point>
				<point>746.000000,106.000000</point>
				<point>738.000000,102.000000</point>
				<point>746.000000,86.000000</point>
				<point>755.000000,90.000000</point>
			</points>
		</object>
		<object>
			<coordinate>pixel</coordinate>
			<type>rectangle</type>
			<description>None</description>
			<possibleresult>
				<name>Small Car</name>
			</possibleresult>
			<points>
				<point>897.000000,147.000000</point>
				<point>893.000000,154.000000</point>
				<point>872.000000,143.000000</point>
				<point>876.000000,136.000000</point>
				<point>897.000000,147.000000</point>
			</points>
		</object>
		<object>
			<coordinate>pixel</coordinate>
			<type>rectangle</type>
			<description>None</description>
			<possibleresult>
				<name>Van</name>
			</possibleresult>
			<points>
				<point>967.000000,149.000000</point>
				<point>956.000000,163.000000</point>
				<point>951.000000,158.000000</point>
				<point>961.000000,145.000000</point>
				<point>967.000000,149.000000</point>
			</points>
		</object>
		<object>
			<coordinate>pixel</coordinate>
			<type>rectangle</type>
			<description>None</description>
			<possibleresult>
				<name>Van</name>
			</possibleresult>
			<points>
				<point>980.000000,159.000000</point>
				<point>969.000000,172.000000</point>
				<point>963.000000,167.000000</point>
				<point>974.000000,154.000000</point>
				<point>980.000000,159.000000</point>
			</points>
		</object>
		<object>
			<coordinate>pixel</coordinate>
			<type>rectangle</type>
			<description>None</description>
			<possibleresult>
				<name>Small Car</name>
			</possibleresult>
			<points>
				<point>918.000000,528.000000</point>
				<point>915.000000,534.000000</point>
				<point>901.000000,527.000000</point>
				<point>904.000000,521.000000</point>
				<point>918.000000,528.000000</point>
			</points>
		</object>
		<object>
			<coordinate>pixel</coordinate>
			<type>rectangle</type>
			<description>None</description>
			<possibleresult>
				<name>Van</name>
			</possibleresult>
			<points>
				<point>917.000000,539.000000</point>
				<point>914.000000,544.000000</point>
				<point>898.000000,537.000000</point>
				<point>900.000000,532.000000</point>
				<point>917.000000,539.000000</point>
			</points>
		</object>
		<object>
			<coordinate>pixel</coordinate>
			<type>rectangle</type>
			<description>None</description>
			<possibleresult>
				<name>Van</name>
			</possibleresult>
			<points>
				<point>911.000000,546.000000</point>
				<point>908.000000,552.000000</point>
				<point>889.000000,545.000000</point>
				<point>892.000000,539.000000</point>
				<point>911.000000,546.000000</point>
			</points>
		</object>
		<object>
			<coordinate>pixel</coordinate>
			<type>rectangle</type>
			<description>None</description>
			<possibleresult>
				<name>Van</name>
			</possibleresult>
			<points>
				<point>476.000000,533.000000</point>
				<point>471.000000,546.000000</point>
				<point>465.000000,543.000000</point>
				<point>470.000000,531.000000</point>
				<point>476.000000,533.000000</point>
			</points>
		</object>
		<object>
			<coordinate>pixel</coordinate>
			<type>rectangle</type>
			<description>None</description>
			<possibleresult>
				<name>Dump Truck</name>
			</possibleresult>
			<points>
				<point>682.000000,738.000000</point>
				<point>675.000000,743.000000</point>
				<point>664.000000,728.000000</point>
				<point>671.000000,723.000000</point>
				<point>682.000000,738.000000</point>
			</points>
		</object>
		<object>
			<coordinate>pixel</coordinate>
			<type>rectangle</type>
			<description>None</description>
			<possibleresult>
				<name>Van</name>
			</possibleresult>
			<points>
				<point>100.999962,994.000000</point>
				<point>96.714249,1000.000000</point>
				<point>85.142792,1000.000000</point>
				<point>93.337807,988.526978</point>
				<point>100.999962,994.000000</point>
			</points>
		</object>
		<object>
			<coordinate>pixel</coordinate>
			<type>rectangle</type>
			<description>None</description>
			<possibleresult>
				<name>Van</name>
			</possibleresult>
			<points>
				<point>161.000000,989.000000</point>
				<point>159.000000,996.000000</point>
				<point>140.000000,990.000000</point>
				<point>142.000000,983.000000</point>
				<point>161.000000,989.000000</point>
			</points>
		</object>
	</objects>
</annotation>