<?xml version="1.0" encoding="utf-8"?>
<annotation>
	<source>
		<filename>228.tif</filename>
		<origin>GF2/GF3</origin>
	</source>
	<research>
		<version>1.0</version>
		<provider>FAIR1M</provider>
		<author>Cyber</author>
		<pluginname>FAIR1M</pluginname>
		<pluginclass>object detection</pluginclass>
		<time>2021-07-21</time>
	</research>
	<size>
		<width>1500</width>
		<height>1500</height>
		<depth>3</depth>
	</size>
	<objects>
		<object>
			<coordinate>pixel</coordinate>
			<type>rectangle</type>
			<description>None</description>
			<possibleresult>
				<name>Dry Cargo Ship</name>
			</possibleresult>
			<points>
				<point>1032.000000,275.000000</point>
				<point>784.000000,147.000000</point>
				<point>767.000000,182.000000</point>
				<point>1015.000000,310.000000</point>
				<point>1032.000000,275.000000</point>
			</points>
		</object>
		<object>
			<coordinate>pixel</coordinate>
			<type>rectangle</type>
			<description>None</description>
			<possibleresult>
				<name>Dry Cargo Ship</name>
			</possibleresult>
			<points>
				<point>691.000000,128.000000</point>
				<point>418.000000,209.000000</point>
				<point>428.000000,248.000000</point>
				<point>701.000000,168.000000</point>
				<point>691.000000,128.000000</point>
			</points>
		</object>
		<object>
			<coordinate>pixel</coordinate>
			<type>rectangle</type>
			<description>None</description>
			<possibleresult>
				<name>Liquid Cargo Ship</name>
			</possibleresult>
			<points>
				<point>103.000000,345.000000</point>
				<point>307.000000,285.000000</point>
				<point>298.000000,253.000000</point>
				<point>94.000000,312.000000</point>
				<point>103.000000,345.000000</point>
			</points>
		</object>
		<object>
			<coordinate>pixel</coordinate>
			<type>rectangle</type>
			<description>None</description>
			<possibleresult>
				<name>Fishing Boat</name>
			</possibleresult>
			<points>
				<point>597.000000,1356.000000</point>
				<point>552.000000,1357.000000</point>
				<point>552.000000,1369.000000</point>
				<point>598.000000,1367.000000</point>
				<point>597.000000,1356.000000</point>
			</points>
		</object>
		<object>
			<coordinate>pixel</coordinate>
			<type>rectangle</type>
			<description>None</description>
			<possibleresult>
				<name>Fishing Boat</name>
			</possibleresult>
			<points>
				<point>605.000000,1367.000000</point>
				<point>550.000000,1371.000000</point>
				<point>551.000000,1380.000000</point>
				<point>606.000000,1376.000000</point>
				<point>605.000000,1367.000000</point>
			</points>
		</object>
		<object>
			<coordinate>pixel</coordinate>
			<type>rectangle</type>
			<description>None</description>
			<possibleresult>
				<name>Fishing Boat</name>
			</possibleresult>
			<points>
				<point>573.000000,1379.000000</point>
				<point>541.000000,1400.000000</point>
				<point>547.000000,1410.000000</point>
				<point>578.000000,1387.000000</point>
				<point>573.000000,1379.000000</point>
			</points>
		</object>
		<object>
			<coordinate>pixel</coordinate>
			<type>rectangle</type>
			<description>None</description>
			<possibleresult>
				<name>Fishing Boat</name>
			</possibleresult>
			<points>
				<point>613.000000,1376.000000</point>
				<point>579.000000,1380.000000</point>
				<point>580.000000,1389.000000</point>
				<point>615.000000,1385.000000</point>
				<point>613.000000,1376.000000</point>
			</points>
		</object>
		<object>
			<coordinate>pixel</coordinate>
			<type>rectangle</type>
			<description>None</description>
			<possibleresult>
				<name>Fishing Boat</name>
			</possibleresult>
			<points>
				<point>580.000000,1389.000000</point>
				<point>549.000000,1410.000000</point>
				<point>554.000000,1420.000000</point>
				<point>586.000000,1400.000000</point>
				<point>580.000000,1389.000000</point>
			</points>
		</object>
		<object>
			<coordinate>pixel</coordinate>
			<type>rectangle</type>
			<description>None</description>
			<possibleresult>
				<name>Fishing Boat</name>
			</possibleresult>
			<points>
				<point>618.000000,1382.000000</point>
				<point>584.000000,1401.000000</point>
				<point>590.000000,1409.000000</point>
				<point>623.000000,1392.000000</point>
				<point>618.000000,1382.000000</point>
			</points>
		</object>
		<object>
			<coordinate>pixel</coordinate>
			<type>rectangle</type>
			<description>None</description>
			<possibleresult>
				<name>Fishing Boat</name>
			</possibleresult>
			<points>
				<point>584.000000,1404.000000</point>
				<point>548.000000,1423.000000</point>
				<point>552.000000,1432.000000</point>
				<point>590.000000,1413.000000</point>
				<point>584.000000,1404.000000</point>
			</points>
		</object>
		<object>
			<coordinate>pixel</coordinate>
			<type>rectangle</type>
			<description>None</description>
			<possibleresult>
				<name>Fishing Boat</name>
			</possibleresult>
			<points>
				<point>622.000000,1395.000000</point>
				<point>584.000000,1415.000000</point>
				<point>590.000000,1427.000000</point>
				<point>626.000000,1406.000000</point>
				<point>622.000000,1395.000000</point>
			</points>
		</object>
		<object>
			<coordinate>pixel</coordinate>
			<type>rectangle</type>
			<description>None</description>
			<possibleresult>
				<name>Fishing Boat</name>
			</possibleresult>
			<points>
				<point>583.000000,1419.000000</point>
				<point>544.000000,1438.000000</point>
				<point>549.000000,1450.000000</point>
				<point>590.000000,1429.000000</point>
				<point>583.000000,1419.000000</point>
			</points>
		</object>
		<object>
			<coordinate>pixel</coordinate>
			<type>rectangle</type>
			<description>None</description>
			<possibleresult>
				<name>Fishing Boat</name>
			</possibleresult>
			<points>
				<point>580.000000,1445.000000</point>
				<point>559.000000,1490.000000</point>
				<point>572.000000,1495.000000</point>
				<point>593.000000,1451.000000</point>
				<point>580.000000,1445.000000</point>
			</points>
		</object>
		<object>
			<coordinate>pixel</coordinate>
			<type>rectangle</type>
			<description>None</description>
			<possibleresult>
				<name>Fishing Boat</name>
			</possibleresult>
			<points>
				<point>579.000000,1448.000000</point>
				<point>630.000000,1421.000000</point>
				<point>625.000000,1411.000000</point>
				<point>575.000000,1437.000000</point>
				<point>579.000000,1448.000000</point>
			</points>
		</object>
		<object>
			<coordinate>pixel</coordinate>
			<type>rectangle</type>
			<description>None</description>
			<possibleresult>
				<name>Fishing Boat</name>
			</possibleresult>
			<points>
				<point>608.000000,1450.000000</point>
				<point>639.000000,1432.000000</point>
				<point>632.000000,1421.000000</point>
				<point>602.000000,1438.000000</point>
				<point>608.000000,1450.000000</point>
			</points>
		</object>
		<object>
			<coordinate>pixel</coordinate>
			<type>rectangle</type>
			<description>None</description>
			<possibleresult>
				<name>Fishing Boat</name>
			</possibleresult>
			<points>
				<point>600.000000,1439.000000</point>
				<point>578.000000,1487.000000</point>
				<point>590.000000,1492.000000</point>
				<point>611.000000,1445.000000</point>
				<point>600.000000,1439.000000</point>
			</points>
		</object>
		<object>
			<coordinate>pixel</coordinate>
			<type>rectangle</type>
			<description>None</description>
			<possibleresult>
				<name>Fishing Boat</name>
			</possibleresult>
			<points>
				<point>611.000000,1446.000000</point>
				<point>592.000000,1495.000000</point>
				<point>602.000000,1498.000000</point>
				<point>623.000000,1451.000000</point>
				<point>611.000000,1446.000000</point>
			</points>
		</object>
		<object>
			<coordinate>pixel</coordinate>
			<type>rectangle</type>
			<description>None</description>
			<possibleresult>
				<name>Fishing Boat</name>
			</possibleresult>
			<points>
				<point>650.000000,1353.000000</point>
				<point>624.000000,1412.000000</point>
				<point>631.000000,1415.000000</point>
				<point>658.000000,1356.000000</point>
				<point>650.000000,1353.000000</point>
			</points>
		</object>
		<object>
			<coordinate>pixel</coordinate>
			<type>rectangle</type>
			<description>None</description>
			<possibleresult>
				<name>Fishing Boat</name>
			</possibleresult>
			<points>
				<point>650.000000,1378.000000</point>
				<point>630.000000,1420.000000</point>
				<point>640.000000,1425.000000</point>
				<point>658.000000,1381.000000</point>
				<point>650.000000,1378.000000</point>
			</points>
		</object>
		<object>
			<coordinate>pixel</coordinate>
			<type>rectangle</type>
			<description>None</description>
			<possibleresult>
				<name>Fishing Boat</name>
			</possibleresult>
			<points>
				<point>659.000000,1390.000000</point>
				<point>642.000000,1422.000000</point>
				<point>652.000000,1429.000000</point>
				<point>670.000000,1395.000000</point>
				<point>659.000000,1390.000000</point>
			</points>
		</object>
		<object>
			<coordinate>pixel</coordinate>
			<type>rectangle</type>
			<description>None</description>
			<possibleresult>
				<name>Fishing Boat</name>
			</possibleresult>
			<points>
				<point>670.000000,1437.000000</point>
				<point>680.000000,1418.000000</point>
				<point>675.000000,1414.000000</point>
				<point>665.000000,1436.000000</point>
				<point>670.000000,1437.000000</point>
			</points>
		</object>
		<object>
			<coordinate>pixel</coordinate>
			<type>rectangle</type>
			<description>None</description>
			<possibleresult>
				<name>Fishing Boat</name>
			</possibleresult>
			<points>
				<point>675.000000,1440.000000</point>
				<point>683.000000,1425.000000</point>
				<point>678.000000,1422.000000</point>
				<point>671.000000,1438.000000</point>
				<point>675.000000,1440.000000</point>
			</points>
		</object>
		<object>
			<coordinate>pixel</coordinate>
			<type>rectangle</type>
			<description>None</description>
			<possibleresult>
				<name>Fishing Boat</name>
			</possibleresult>
			<points>
				<point>679.000000,1446.000000</point>
				<point>691.000000,1426.000000</point>
				<point>685.000000,1422.000000</point>
				<point>675.000000,1444.000000</point>
				<point>679.000000,1446.000000</point>
			</points>
		</object>
		<object>
			<coordinate>pixel</coordinate>
			<type>rectangle</type>
			<description>None</description>
			<possibleresult>
				<name>Fishing Boat</name>
			</possibleresult>
			<points>
				<point>684.000000,1451.000000</point>
				<point>696.000000,1431.000000</point>
				<point>691.000000,1429.000000</point>
				<point>680.000000,1448.000000</point>
				<point>684.000000,1451.000000</point>
			</points>
		</object>
		<object>
			<coordinate>pixel</coordinate>
			<type>rectangle</type>
			<description>None</description>
			<possibleresult>
				<name>Fishing Boat</name>
			</possibleresult>
			<points>
				<point>692.000000,1454.000000</point>
				<point>705.000000,1432.000000</point>
				<point>700.000000,1429.000000</point>
				<point>686.000000,1450.000000</point>
				<point>692.000000,1454.000000</point>
			</points>
		</object>
		<object>
			<coordinate>pixel</coordinate>
			<type>rectangle</type>
			<description>None</description>
			<possibleresult>
				<name>Fishing Boat</name>
			</possibleresult>
			<points>
				<point>698.000000,1457.000000</point>
				<point>707.000000,1440.000000</point>
				<point>703.000000,1437.000000</point>
				<point>693.000000,1454.000000</point>
				<point>698.000000,1457.000000</point>
			</points>
		</object>
		<object>
			<coordinate>pixel</coordinate>
			<type>rectangle</type>
			<description>None</description>
			<possibleresult>
				<name>Fishing Boat</name>
			</possibleresult>
			<points>
				<point>693.000000,1462.000000</point>
				<point>670.000000,1446.000000</point>
				<point>665.000000,1453.000000</point>
				<point>688.000000,1469.000000</point>
				<point>693.000000,1462.000000</point>
			</points>
		</object>
		<object>
			<coordinate>pixel</coordinate>
			<type>rectangle</type>
			<description>None</description>
			<possibleresult>
				<name>Fishing Boat</name>
			</possibleresult>
			<points>
				<point>688.000000,1469.000000</point>
				<point>660.000000,1460.000000</point>
				<point>659.000000,1464.000000</point>
				<point>685.000000,1473.000000</point>
				<point>688.000000,1469.000000</point>
			</points>
		</object>
		<object>
			<coordinate>pixel</coordinate>
			<type>rectangle</type>
			<description>None</description>
			<possibleresult>
				<name>Fishing Boat</name>
			</possibleresult>
			<points>
				<point>685.000000,1475.000000</point>
				<point>659.000000,1465.000000</point>
				<point>656.000000,1471.000000</point>
				<point>683.000000,1480.000000</point>
				<point>685.000000,1475.000000</point>
			</points>
		</object>
		<object>
			<coordinate>pixel</coordinate>
			<type>rectangle</type>
			<description>None</description>
			<possibleresult>
				<name>Fishing Boat</name>
			</possibleresult>
			<points>
				<point>694.000000,1463.000000</point>
				<point>676.000000,1497.000000</point>
				<point>682.000000,1501.000000</point>
				<point>700.000000,1467.000000</point>
				<point>694.000000,1463.000000</point>
			</points>
		</object>
		<object>
			<coordinate>pixel</coordinate>
			<type>rectangle</type>
			<description>None</description>
			<possibleresult>
				<name>Fishing Boat</name>
			</possibleresult>
			<points>
				<point>699.000000,1472.000000</point>
				<point>696.000000,1503.000000</point>
				<point>700.000000,1503.000000</point>
				<point>703.000000,1473.000000</point>
				<point>699.000000,1472.000000</point>
			</points>
		</object>
		<object>
			<coordinate>pixel</coordinate>
			<type>rectangle</type>
			<description>None</description>
			<possibleresult>
				<name>Fishing Boat</name>
			</possibleresult>
			<points>
				<point>704.000000,1477.000000</point>
				<point>702.000000,1504.000000</point>
				<point>707.000000,1504.000000</point>
				<point>710.000000,1477.000000</point>
				<point>704.000000,1477.000000</point>
			</points>
		</object>
		<object>
			<coordinate>pixel</coordinate>
			<type>rectangle</type>
			<description>None</description>
			<possibleresult>
				<name>Fishing Boat</name>
			</possibleresult>
			<points>
				<point>724.000000,1480.000000</point>
				<point>735.000000,1461.000000</point>
				<point>731.000000,1459.000000</point>
				<point>720.000000,1478.000000</point>
				<point>724.000000,1480.000000</point>
			</points>
		</object>
		<object>
			<coordinate>pixel</coordinate>
			<type>rectangle</type>
			<description>None</description>
			<possibleresult>
				<name>Fishing Boat</name>
			</possibleresult>
			<points>
				<point>729.000000,1485.000000</point>
				<point>742.000000,1463.000000</point>
				<point>738.000000,1461.000000</point>
				<point>725.000000,1481.000000</point>
				<point>729.000000,1485.000000</point>
			</points>
		</object>
		<object>
			<coordinate>pixel</coordinate>
			<type>rectangle</type>
			<description>None</description>
			<possibleresult>
				<name>Fishing Boat</name>
			</possibleresult>
			<points>
				<point>735.000000,1487.000000</point>
				<point>747.000000,1467.000000</point>
				<point>743.000000,1464.000000</point>
				<point>731.000000,1485.000000</point>
				<point>735.000000,1487.000000</point>
			</points>
		</object>
		<object>
			<coordinate>pixel</coordinate>
			<type>rectangle</type>
			<description>None</description>
			<possibleresult>
				<name>Fishing Boat</name>
			</possibleresult>
			<points>
				<point>735.000000,1456.000000</point>
				<point>749.000000,1438.000000</point>
				<point>744.000000,1436.000000</point>
				<point>731.000000,1454.000000</point>
				<point>735.000000,1456.000000</point>
			</points>
		</object>
		<object>
			<coordinate>pixel</coordinate>
			<type>rectangle</type>
			<description>None</description>
			<possibleresult>
				<name>Fishing Boat</name>
			</possibleresult>
			<points>
				<point>741.000000,1459.000000</point>
				<point>752.000000,1440.000000</point>
				<point>750.000000,1438.000000</point>
				<point>738.000000,1456.000000</point>
				<point>741.000000,1459.000000</point>
			</points>
		</object>
		<object>
			<coordinate>pixel</coordinate>
			<type>rectangle</type>
			<description>None</description>
			<possibleresult>
				<name>Fishing Boat</name>
			</possibleresult>
			<points>
				<point>748.000000,1461.000000</point>
				<point>758.000000,1445.000000</point>
				<point>754.000000,1442.000000</point>
				<point>744.000000,1457.000000</point>
				<point>748.000000,1461.000000</point>
			</points>
		</object>
		<object>
			<coordinate>pixel</coordinate>
			<type>rectangle</type>
			<description>None</description>
			<possibleresult>
				<name>Fishing Boat</name>
			</possibleresult>
			<points>
				<point>748.000000,1437.000000</point>
				<point>756.000000,1419.000000</point>
				<point>752.000000,1417.000000</point>
				<point>744.000000,1434.000000</point>
				<point>748.000000,1437.000000</point>
			</points>
		</object>
		<object>
			<coordinate>pixel</coordinate>
			<type>rectangle</type>
			<description>None</description>
			<possibleresult>
				<name>Fishing Boat</name>
			</possibleresult>
			<points>
				<point>752.000000,1438.000000</point>
				<point>765.000000,1414.000000</point>
				<point>761.000000,1413.000000</point>
				<point>750.000000,1437.000000</point>
				<point>752.000000,1438.000000</point>
			</points>
		</object>
		<object>
			<coordinate>pixel</coordinate>
			<type>rectangle</type>
			<description>None</description>
			<possibleresult>
				<name>Fishing Boat</name>
			</possibleresult>
			<points>
				<point>757.000000,1440.000000</point>
				<point>770.000000,1418.000000</point>
				<point>767.000000,1417.000000</point>
				<point>754.000000,1438.000000</point>
				<point>757.000000,1440.000000</point>
			</points>
		</object>
		<object>
			<coordinate>pixel</coordinate>
			<type>rectangle</type>
			<description>None</description>
			<possibleresult>
				<name>Fishing Boat</name>
			</possibleresult>
			<points>
				<point>765.000000,1442.000000</point>
				<point>775.000000,1420.000000</point>
				<point>771.000000,1419.000000</point>
				<point>760.000000,1439.000000</point>
				<point>765.000000,1442.000000</point>
			</points>
		</object>
		<object>
			<coordinate>pixel</coordinate>
			<type>rectangle</type>
			<description>None</description>
			<possibleresult>
				<name>Fishing Boat</name>
			</possibleresult>
			<points>
				<point>756.000000,1412.000000</point>
				<point>781.000000,1420.000000</point>
				<point>783.000000,1414.000000</point>
				<point>759.000000,1405.000000</point>
				<point>756.000000,1412.000000</point>
			</points>
		</object>
		<object>
			<coordinate>pixel</coordinate>
			<type>rectangle</type>
			<description>None</description>
			<possibleresult>
				<name>Intersection</name>
			</possibleresult>
			<points>
				<point>439.000000,1132.000000</point>
				<point>467.000000,1081.000000</point>
				<point>516.000000,1108.000000</point>
				<point>487.000000,1159.000000</point>
				<point>439.000000,1132.000000</point>
			</points>
		</object>
		<object>
			<coordinate>pixel</coordinate>
			<type>rectangle</type>
			<description>None</description>
			<possibleresult>
				<name>Intersection</name>
			</possibleresult>
			<points>
				<point>971.000000,1412.000000</point>
				<point>999.000000,1361.000000</point>
				<point>1047.000000,1387.000000</point>
				<point>1019.000000,1439.000000</point>
				<point>971.000000,1412.000000</point>
			</points>
		</object>
		<object>
			<coordinate>pixel</coordinate>
			<type>rectangle</type>
			<description>None</description>
			<possibleresult>
				<name>Intersection</name>
			</possibleresult>
			<points>
				<point>109.000000,953.000000</point>
				<point>132.000000,911.000000</point>
				<point>194.000000,944.000000</point>
				<point>170.000000,987.000000</point>
				<point>109.000000,953.000000</point>
			</points>
		</object>
		<object>
			<coordinate>pixel</coordinate>
			<type>rectangle</type>
			<description>None</description>
			<possibleresult>
				<name>Intersection</name>
			</possibleresult>
			<points>
				<point>252.000000,1471.000000</point>
				<point>271.000000,1436.000000</point>
				<point>303.000000,1454.000000</point>
				<point>285.000000,1489.000000</point>
				<point>252.000000,1471.000000</point>
			</points>
		</object>
	</objects>
</annotation>