<?xml version="1.0" encoding="utf-8"?>
<annotation>
	<source>
		<filename>855.tif</filename>
		<origin>GF2/GF3</origin>
	</source>
	<research>
		<version>1.0</version>
		<provider>FAIR1M</provider>
		<author>Cyber</author>
		<pluginname>FAIR1M</pluginname>
		<pluginclass>object detection</pluginclass>
		<time>2021-07-21</time>
	</research>
	<size>
		<width>1000</width>
		<height>1000</height>
		<depth>3</depth>
	</size>
	<objects>
		<object>
			<coordinate>pixel</coordinate>
			<type>rectangle</type>
			<description>None</description>
			<possibleresult>
				<name>Boeing737</name>
			</possibleresult>
			<points>
				<point>-15.000000,922.000000</point>
				<point>30.000000,943.000000</point>
				<point>50.000000,902.000000</point>
				<point>4.000000,879.000000</point>
				<point>-15.000000,922.000000</point>
			</points>
		</object>
		<object>
			<coordinate>pixel</coordinate>
			<type>rectangle</type>
			<description>None</description>
			<possibleresult>
				<name>A220</name>
			</possibleresult>
			<points>
				<point>355.000000,875.000000</point>
				<point>385.000000,838.000000</point>
				<point>350.000000,809.000000</point>
				<point>321.000000,845.000000</point>
				<point>355.000000,875.000000</point>
			</points>
		</object>
		<object>
			<coordinate>pixel</coordinate>
			<type>rectangle</type>
			<description>None</description>
			<possibleresult>
				<name>A220</name>
			</possibleresult>
			<points>
				<point>321.000000,672.000000</point>
				<point>360.000000,706.000000</point>
				<point>391.000000,670.000000</point>
				<point>350.000000,638.000000</point>
				<point>321.000000,672.000000</point>
			</points>
		</object>
		<object>
			<coordinate>pixel</coordinate>
			<type>rectangle</type>
			<description>None</description>
			<possibleresult>
				<name>Boeing737</name>
			</possibleresult>
			<points>
				<point>799.000000,163.000000</point>
				<point>833.000000,195.000000</point>
				<point>864.000000,161.000000</point>
				<point>828.000000,129.000000</point>
				<point>799.000000,163.000000</point>
			</points>
		</object>
		<object>
			<coordinate>pixel</coordinate>
			<type>rectangle</type>
			<description>None</description>
			<possibleresult>
				<name>Intersection</name>
			</possibleresult>
			<points>
				<point>223.000000,205.000000</point>
				<point>236.000000,217.000000</point>
				<point>248.000000,204.000000</point>
				<point>235.000000,193.000000</point>
				<point>223.000000,205.000000</point>
			</points>
		</object>
		<object>
			<coordinate>pixel</coordinate>
			<type>rectangle</type>
			<description>None</description>
			<possibleresult>
				<name>Intersection</name>
			</possibleresult>
			<points>
				<point>351.000000,317.000000</point>
				<point>364.000000,329.000000</point>
				<point>375.000000,316.000000</point>
				<point>362.000000,305.000000</point>
				<point>351.000000,317.000000</point>
			</points>
		</object>
	</objects>
</annotation>